vibranium-sdk/__init__.py
vibranium-sdk/__main__.py
vibranium-sdk/utils.py
vibranium-sdk/vibranium.py
vibranium_sdk/__init__.py
vibranium_sdk/__main__.py
vibranium_sdk/utils.py
vibranium_sdk/vibranium.py
vibranium_sdk-0.1.1.dist-info/LICENSE
vibranium_sdk-0.1.1.dist-info/METADATA
vibranium_sdk-0.1.1.dist-info/WHEEL
vibranium_sdk-0.1.1.dist-info/entry_points.txt
vibranium_sdk-0.1.1.dist-info/top_level.txt
vibranium_sdk-0.1.1.dist-info/RECORD
